featureng/__init__.py
featureng/bq.py
featureng/datetime.py
featureng/exceptions.py
featureng/external.py
featureng/interaction.py
featureng/outliers.py
featureng/scale.py
featureng/transform.py
featureng-0.0.1.dist-info/LICENSE
featureng-0.0.1.dist-info/METADATA
featureng-0.0.1.dist-info/WHEEL
featureng-0.0.1.dist-info/top_level.txt
featureng-0.0.1.dist-info/RECORD
