Metadata-Version: 2.1
Name: featureng
Version: 0.0.1
Summary: Library for feature engineering
Home-page: https://github.com/pypa/sampleproject
Author: Austin Poor
Author-email: austinpoor@gmail.com
License: UNKNOWN
Platform: UNKNOWN
Classifier: Programming Language :: Python :: 3.6
Classifier: Programming Language :: Python :: 3.7
Classifier: Programming Language :: Python :: 3.8
Classifier: License :: OSI Approved :: GNU General Public License v3 (GPLv3)
Classifier: Operating System :: OS Independent
Classifier: Development Status :: 1 - Planning
Requires-Python: >=3.6
